.travis.yml
MANIFEST.in
README.rst
bootstrap-buildout.py
buildout.cfg
requirements.txt
setup.py
version.txt
bob/__init__.py
bob.db.avspoof_btas2016.egg-info/PKG-INFO
bob.db.avspoof_btas2016.egg-info/SOURCES.txt
bob.db.avspoof_btas2016.egg-info/dependency_links.txt
bob.db.avspoof_btas2016.egg-info/entry_points.txt
bob.db.avspoof_btas2016.egg-info/not-zip-safe
bob.db.avspoof_btas2016.egg-info/requires.txt
bob.db.avspoof_btas2016.egg-info/top_level.txt
bob/db/__init__.py
bob/db/avspoof_btas2016/__init__.py
bob/db/avspoof_btas2016/checkfiles.py
bob/db/avspoof_btas2016/create.py
bob/db/avspoof_btas2016/db.sql3
bob/db/avspoof_btas2016/db_.sql3
bob/db/avspoof_btas2016/debug_avspoof_btas2016.py
bob/db/avspoof_btas2016/driver.py
bob/db/avspoof_btas2016/dumplist.py
bob/db/avspoof_btas2016/models.py
bob/db/avspoof_btas2016/query.py
bob/db/avspoof_btas2016/spoofing.py
bob/db/avspoof_btas2016/test.py
bob/db/avspoof_btas2016/verification.py
bob/db/avspoof_btas2016/protocols/attack-btas2016-allsupports-devel.txt
bob/db/avspoof_btas2016/protocols/attack-btas2016-allsupports-test.txt
bob/db/avspoof_btas2016/protocols/attack-btas2016-allsupports-train.txt
bob/db/avspoof_btas2016/protocols/clients-grandtest-allsupports.txt
bob/db/avspoof_btas2016/protocols/generate_dblists.py
bob/db/avspoof_btas2016/protocols/real-btas2016-allsupports-devel.txt
bob/db/avspoof_btas2016/protocols/real-btas2016-allsupports-test.txt
bob/db/avspoof_btas2016/protocols/real-btas2016-allsupports-train.txt
doc/conf.py
doc/guide.rst
doc/index.rst
doc/py_api.rst
doc/img/favicon.ico
doc/img/logo.png