Metadata-Version: 1.1
Name: bob.db.avspoof-btas2016
Version: 1.0.1
Summary: Audio AVspoof Attack Database Access API for BTAS 2016 Speaker Anti-spoofing Competition
Home-page: http://github.com/bioidiap/bob.db.avspoof_btas2016
Author: Pavel Korshunov
Author-email: pavel.korshunov@idiap.ch
License: GPLv3
Platform: UNKNOWN
Classifier: Framework :: Bob
Classifier: Development Status :: 4 - Beta
Classifier: Intended Audience :: Science/Research
Classifier: License :: OSI Approved :: GNU General Public License v3 (GPLv3)
Classifier: Natural Language :: English
Classifier: Programming Language :: Python
Classifier: Programming Language :: Python :: 3
Classifier: Topic :: Scientific/Engineering :: Artificial Intelligence
Classifier: Topic :: Database :: Front-Ends
